Metadata-Version: 2.4
Name: svpg
Version: 1.4.1
Summary: A pangenome-based structural variant caller
Author: henghu
Author-email: hhengwork@gmail.com
License: MIT
Requires-Python: >=3.10
License-File: LICENSE
Requires-Dist: numpy>=1.26.4
Requires-Dist: pysam>=0.22
Requires-Dist: scipy>=1.13.1
Requires-Dist: pyabpoa>=1.5.4
Dynamic: author
Dynamic: author-email
Dynamic: description
Dynamic: description-content-type
Dynamic: license
Dynamic: license-file
Dynamic: requires-dist
Dynamic: requires-python
Dynamic: summary
